{
  "docId": "sotsiaaltoo-1-2025",
  "year": 2025,
  "journalTitle": "Sotsiaaltöö",
  "issueLabel": "1/2025",
  "audience": "BOTH",
  "language": "et",
  "source_type": "file",
  "articleId": "eessona-2025-1",
  "title": "Eessõna",
  "authors": [
    "Reeli Sirotkina"
  ],
  "section": "Eessõna",
  "pdf_start_page": 1,
  "pdf_end_page": 2,
  "description": "Eessõnas avab sotsiaaltöö uurija Reeli Sirotkina numbri 1/2025 fookuse: solidaarsusele, ebavõrdsuse leevendamisele ja sotsiaalse jätkusuutlikkuse küsimustele suunatud sotsiaaltöö. Autor seob tänased väljakutsed – vaesuse, ebavõrdsuse, ebastabiilse tööturu ja globaalsete kriiside mõjud – sotsiaaltöö ajaloolise rolliga ning küsib, milliseid suundi valisime 1990. aastatel ja mida neist on tänases Eestis vaja ümber mõtestada. Samuti tutvustab ta numbri olulisemaid teemasid: vanuseline diskrimineerimine, piirkondlik ebavõrdsus, võrdõiguslikkus tööturul, Ukraina sõjapõgenike toetamine ja solidaarsusel põhinev heaoluühiskond.",
  "tags": [
    "eessõna",
    "solidaarsus",
    "ebavõrdsus",
    "sotsiaalne jätkusuutlikkus",
    "sotsiaaltöö roll",
    "heaoluriik"
  ],
  "source_path": "Eessõna 1_2025 _ Tervise Arengu Instituut.pdf"
}