{
  "docId": "sotsiaaltoo-4-2019",
  "articleId": "katseprojekt-hoolduse-koord-2019",
  "title": "Katseprojekt kinnitas hoolduse koordineerimise vajalikkust",
  "authors": [
    "Gerli Aavik-Märtmaa"
  ],
  "year": 2019,
  "journalTitle": "Sotsiaaltöö",
  "issueLabel": "4/2019",
  "section": "Sotsiaaltöö korraldus",
  "pageRange": "16-19",
  "pdf_start_page": 1,
  "pdf_end_page": 4,
  "audience": "BOTH",
  "language": "et",
  "description": "Artikkel selgitab hoolduse koordineerimise pilootprojekti tulemusi ning tõendab, miks valdkondadevaheline koostöö parandab abi kättesaadavust ja kvaliteeti.",
  "tags": [
    "hoolduse koordineerimine",
    "pilootprojekt",
    "sotsiaaltöö korraldus"
  ],
  "source_type": "file",
  "source_path": "ST4_2019_web_link_Part6.pdf"
}