{
  "docId": "sotsiaaltoo-3-2019",
  "articleId": "lapse-oigus-osaleda-abivajaduse-hindamises-2019",
  "title": "Lapse õigus osaleda abivajaduse hindamises: kuidas lastekaitsetöötajad seda tõlgendavad?",
  "authors": [
    "Karmen Toros"
  ],
  "year": 2019,
  "journalTitle": "Sotsiaaltöö",
  "issueLabel": "3/2019",
  "section": "Lapsesõbralik lastekaitse",
  "pageRange": "27-31",
  "pdf_start_page": 1,
  "pdf_end_page": 5,
  "audience": "BOTH",
  "language": "et",
  "description": "Artikkel käsitleb Harjumaa lastekaitsetöötajate arusaamu ja praktikaid seoses lapse õigusega osaleda abivajaduse hindamise protsessis, tuginedes intervjuupõhise uuringu tulemustele.",
  "tags": [
    "lapse osalus",
    "abivajaduse hindamine",
    "lapsekaitse",
    "lapsesõbralik praktika"
  ],
  "source_type": "file",
  "source_path": "ST3_2019_veeb_link_Part7.pdf"
}