{
  "docId": "sotsiaaltoo-4-2025",
  "articleId": "taastava-oiguse-rakendamise-voimalused-ja-kogemused-2025-4",
  "title": "Taastava õiguse rakendamise võimalused ja kogemused",
  "authors": [
    "Liisi Truumets",
    "Rauni Rohuniit"
  ],
  "year": 2025,
  "journalTitle": "Sotsiaaltöö",
  "issueLabel": "4/2025",
  "section": "Taastav õigus",
  "pageRange": null,
  "pdf_start_page": 1,
  "pdf_end_page": 6,
  "audience": "BOTH",
  "language": "et",
  "description": "Artikkel annab ülevaate taastava õiguse põhimõtetest, kujunemisest ja rakendamisest Eestis, rõhutades ohvri vajaduste, dialoogi ja kahju heastamise tähtsust. Käsitletakse SKA ja PPA koostööd, vahendusmenetluse arengut ning taastava õiguse edasisi sihte.",
  "tags": [
    "taastav õigus",
    "vahendusmenetlus",
    "ohvriabi",
    "kahju heastamine",
    "dialoog",
    "PPA",
    "SKA"
  ],
  "source_type": "file",
  "source_path": "Taastava õiguse rakendamise võimalused ja kogemused.pdf"
}